n3d3/libN3D3.cpython-37m-x86_64-linux-gnu.so
n3d3/__init__.py
n3d3/tensor.py
n3d3-0.0.5.dist-info/top_level.txt
n3d3-0.0.5.dist-info/LICENSE
n3d3-0.0.5.dist-info/METADATA
n3d3-0.0.5.dist-info/RECORD
n3d3-0.0.5.dist-info/WHEEL
